dixonstat/__about__.py
dixonstat/__init__.py
dixonstat/__main__.py
dixonstat/_quadrature.py
dixonstat/_ratio.py
dixonstat-0.1.0a0.dev0.dist-info/METADATA
dixonstat-0.1.0a0.dev0.dist-info/WHEEL
dixonstat-0.1.0a0.dev0.dist-info/licenses/LICENSE
dixonstat-0.1.0a0.dev0.dist-info/RECORD
